bert4pytorch/__init__.py
bert4pytorch/ema.py
bert4pytorch/file_utils.py
bert4pytorch/modeling.py
bert4pytorch/optimization.py
bert4pytorch/snippets.py
bert4pytorch/tokenization.py
bert4pytorch-0.1.2.dist-info/DESCRIPTION.rst
bert4pytorch-0.1.2.dist-info/METADATA
bert4pytorch-0.1.2.dist-info/RECORD
bert4pytorch-0.1.2.dist-info/WHEEL
bert4pytorch-0.1.2.dist-info/metadata.json
bert4pytorch-0.1.2.dist-info/top_level.txt
